iteround/__init__.py
iteround/core.py
iteround-1.0.2.dist-info/METADATA
iteround-1.0.2.dist-info/RECORD
iteround-1.0.2.dist-info/WHEEL
iteround-1.0.2.dist-info/top_level.txt
tests/__init__.py
tests/test_saferound.py
