Metadata-Version: 2.1
Name: iteround
Version: 1.0.2
Summary: Rounds iterables (arrays, lists, sets, etc) while maintaining the sum of the initial array.
Home-page: https://github.com/cgdeboer/iteround
Author: Calvin DeBoer
Author-email: cgdeboer@gmail.com
License: UNKNOWN
Platform: UNKNOWN
Classifier: Programming Language :: Python :: 3
Classifier: Programming Language :: Python :: 2
Classifier: License :: OSI Approved :: MIT License
Classifier: Operating System :: OS Independent
